atlisp/__init__.py
atlisp/__main__.py
atlisp/atlisp.py
atlisp/find.py
atlisp/proxy.py
atlisp-0.3.46.dist-info/METADATA
atlisp-0.3.46.dist-info/WHEEL
atlisp-0.3.46.dist-info/entry_points.txt
atlisp-0.3.46.dist-info/licenses/LICENSE
atlisp-0.3.46.dist-info/RECORD
