Metadata-Version: 2.4
Name: atlisp
Version: 0.3.46
Summary: @lisp CAD应用云是一个运行于 AutoCAD、中望CAD、浩辰CAD及类似兼容的CAD系统中的应用管理器。用于管理 AutoLisp 程序的网络下载安装、加载、卸载、查询等。可方便地实现 autolisp 程序的云管理。
Project-URL: Homepage, https://atlisp.cn
Author-email: VitalGG <vitalgg@gmail.com>
License: MIT License
License-File: LICENSE
Keywords: @lisp,CAD,CAD应用云,atlisp,autolisp
Classifier: License :: OSI Approved :: MIT License
Classifier: Operating System :: OS Independent
Classifier: Programming Language :: Python :: 3
Requires-Python: >=3.8
Requires-Dist: argparse
Requires-Dist: colorama
Requires-Dist: psutil
Requires-Dist: pywin32>280
Requires-Dist: urllib3
